toughkey/__init__.py
toughkey/toughdes.py
toughkey/toughtoken.so
toughkey-1.0a1.dist-info/DESCRIPTION.rst
toughkey-1.0a1.dist-info/entry_points.txt
toughkey-1.0a1.dist-info/METADATA
toughkey-1.0a1.dist-info/metadata.json
toughkey-1.0a1.dist-info/RECORD
toughkey-1.0a1.dist-info/top_level.txt
toughkey-1.0a1.dist-info/WHEEL
