Metadata-Version: 2.0
Name: toughkey
Version: 1.0a1
Summary: toughcloud keyutils
Home-page: https://github.com/talkincode/txweb
Author: jamiesun
Author-email: jamiesun.net@gmail.com
License: UNKNOWN
Platform: UNKNOWN
